ComputerCommands/__init__.py
ComputerCommands/commands.py
src/__init__.py
src/commands.py
ComputerCommands-2.1.1.dist-info/LICENSE
ComputerCommands-2.1.1.dist-info/METADATA
ComputerCommands-2.1.1.dist-info/WHEEL
ComputerCommands-2.1.1.dist-info/top_level.txt
ComputerCommands-2.1.1.dist-info/RECORD
