Metadata-Version: 2.1
Name: ComputerCommands
Version: 2.1.1
Summary: A Python package for running commands on any operating system.
Home-page: https://github.com/Malacai4/ComputerCommands
Author: Malacai Hiebert
Author-email: malacaihiebert@gmail.com
License: MIT
Platform: UNKNOWN
Classifier: License :: OSI Approved :: MIT License
Classifier: Programming Language :: Python :: 3
Classifier: Programming Language :: Python :: 3.7
Classifier: Programming Language :: Python :: 3.8
